Workbook

Sheet Dashboard
A1: 私募信贷危机监测面板
A2: 作者：DD｜X：@DD29397053｜欢迎关注作者 X 账号，会不定期发布投资类 Skill
A3: 用途：自动汇总 Checklist 中 16 项监测结果，并输出整体风险等级。新闻型指标的详细证据请见 Evidence sheet。
A4: 更新日期 | C4: 指标总数 | E4: 绿灯数 | G4: 黄灯数
C5: =COUNTA(Checklist!A6:A21) | E5: =COUNTIF(Checklist!H6:H21,"绿灯") | G5: =COUNTIF(Checklist!H6:H21,"黄灯")
A7: 红灯数 | C7: 加权分数 | E7: 整体风险等级
A8: =COUNTIF(Checklist!H6:H21,"红灯") | C8: =SUM(Checklist!I6:I21) | E8: =IF(COUNTIF(Checklist!H6:H21,"红灯")>=2,"红灯",IF(OR(COUNTIF(Checklist!H6:H21,"红灯")=1,COUNTIF(Checklist!H6:H21,"黄灯")>=4,SUM(Checklist!I6:I21)>=8),"黄灯","绿灯"))
A10: 使用说明
A11: 1. 程序会自动更新 Checklist 中 16 项指标的状态、状态依据、证据链接、自动化方式与主数据源。
A12: 2. 绿灯=正常；黄灯=压力开始传导；红灯=风险显著；待更新=数据源异常或需人工复核。
A13: 3. 新闻型指标的详细媒体标题、日期与链接，统一写入 Evidence sheet，便于点击核验误报。
A14: 4. 建议优先查看 Dashboard 的整体风险等级，再下钻到 Checklist 和 Evidence。
A15: 5. 可复制本模板，用于美国、欧洲、单一管理人或特定行业的独立跟踪。
A18: 建议优先监测的 5 项
A19: 1. 是否新增大型基金限赎 / Gate
A20: 2. BDC 是否持续折价扩大
A21: 3. HY OAS / 杠杆贷款 / CLO 是否共振走弱
A22: 4. 违约、PIK、重组是否从个案变成簇发
A23: 5. 银行是否开始实质收紧对相关领域授信

Sheet Checklist
A1: 私募信贷危机监测清单（正式版模板）
A2: 程序将自动写入状态、状态依据、证据链接、自动化方式与主数据源；新闻型指标的详细媒体证据见 Evidence sheet。
A5: ID | B5: 层级 | C5: 类别 | D5: 指标 | E5: 频率 | F5: 看什么 | G5: 升级阈值 | H5: 状态 | I5: 分数 | J5: 状态依据（具体数据+来源） | K5: 证据链接 / Evidence IDs | L5: 自动化方式 | M5: 主数据源 | N5: 备注 / 下一步动作
A6: EW-01 | B6: 早期预警 | C6: 流动性 | D6: 是否出现新的限赎 / Gate | E6: 每周 | F6: 大型基金是否新增限赎、延后支付、按比例赎回 | G6: 出现 1 家大型机构=黄灯；连续扩散到多家=红灯 | H6: 待更新 | I6: =IF(H6="待更新","",IF(H6="绿灯",0,IF(H6="黄灯",1,IF(H6="红灯",2,"")))) | L6: 新闻聚类 | M6: Google News RSS / 主流媒体
A7: EW-02 | B7: 早期预警 | C7: 市场价格 | D7: 相关资管股是否持续跑输 | E7: 每周 | F7: BlackRock / Blackstone / Apollo / Ares / Blue Owl / KKR 是否持续弱于大盘和金融板块 | G7: 单周明显跑输=黄灯；连续数周且伴随坏消息=红灯 | H7: 待更新 | I7: =IF(H7="待更新","",IF(H7="绿灯",0,IF(H7="黄灯",1,IF(H7="红灯",2,"")))) | L7: 数值直抓 | M7: Stooq
A8: EW-03 | B8: 早期预警 | C8: 公开市场映射 | D8: BDC 板块是否扩大折价 | E8: 每周 | F8: 上市 BDC 相对 NAV 折价是否扩大，是否弱于 HY | G8: 折价明显扩大=黄灯；行业普遍深折价=红灯 | H8: 待更新 | I8: =IF(H8="待更新","",IF(H8="绿灯",0,IF(H8="黄灯",1,IF(H8="红灯",2,"")))) | L8: 代理数值 | M8: Stooq
A9: EW-04 | B9: 早期预警 | C9: 信用情绪 | D9: HY / 杠杆贷款 / CLO 是否同步走弱 | E9: 每周 | F9: HY OAS、杠杆贷款价格、CLO BBB / BB 利差 | G9: 一个市场走弱=黄灯；多个子市场共振=红灯 | H9: 待更新 | I9: =IF(H9="待更新","",IF(H9="绿灯",0,IF(H9="黄灯",1,IF(H9="红灯",2,"")))) | L9: 数值直抓 | M9: FRED + Stooq
A10: EW-05 | B10: 早期预警 | C10: 舆情密度 | D10: 坏消息是否从个案变成簇发 | E10: 每周 | F10: 欺诈、估值争议、违约、失真抵押品、提款冻结等新闻数量 | G10: 单点个案=黄灯；连续簇发=红灯 | H10: 待更新 | I10: =IF(H10="待更新","",IF(H10="绿灯",0,IF(H10="黄灯",1,IF(H10="红灯",2,"")))) | L10: 新闻聚类 | M10: Google News RSS / 主流媒体
A11: TR-01 | B11: 中期传导 | C11: 信用质量 | D11: 违约 / 重组 / 展期是否增加 | E11: 每月 | F11: 借款人违约、amend-and-extend、债务交换、重组案例 | G11: 违约或重组明显增多=黄灯；行业性增加=红灯 | H11: 待更新 | I11: =IF(H11="待更新","",IF(H11="绿灯",0,IF(H11="黄灯",1,IF(H11="红灯",2,"")))) | L11: 新闻聚类 | M11: Google News RSS / 主流媒体
A12: TR-02 | B12: 中期传导 | C12: 现金流 | D12: PIK 利息是否增多 | E12: 每月 | F12: 越来越多借款人不付现金利息而改为 PIK | G12: PIK 上升=黄灯；PIK 成为常见做法=红灯 | H12: 待更新 | I12: =IF(H12="待更新","",IF(H12="绿灯",0,IF(H12="黄灯",1,IF(H12="红灯",2,"")))) | L12: 新闻聚类 | M12: Google News RSS / 主流媒体
A13: TR-03 | B13: 中期传导 | C13: 估值 | D13: NAV 是否开始连续下修 | E13: 每月 / 每季 | F13: 季度 NAV 是否跟随公开市场信用重定价而下调 | G13: 单次明显下修=黄灯；连续下修且折价扩大=红灯 | H13: 待更新 | I13: =IF(H13="待更新","",IF(H13="绿灯",0,IF(H13="黄灯",1,IF(H13="红灯",2,"")))) | L13: 代理数值 | M13: Stooq
A14: TR-04 | B14: 中期传导 | C14: 募资 | D14: 新基金募资是否明显放缓 | E14: 每月 | F14: 募资周期拉长、规模缩水、零售 / 高净值净流入转负 | G14: 募资放缓=黄灯；普遍募资困难=红灯 | H14: 待更新 | I14: =IF(H14="待更新","",IF(H14="绿灯",0,IF(H14="黄灯",1,IF(H14="红灯",2,"")))) | L14: 新闻聚类 | M14: Google News RSS / 主流媒体
A15: TR-05 | B15: 中期传导 | C15: 交易条款 | D15: 新交易条款是否重新收紧 | E15: 每月 | F15: 票息上升、covenant 收紧、借款人融资更难 | G15: 条款明显变严=黄灯；新交易大量搁置=红灯 | H15: 待更新 | I15: =IF(H15="待更新","",IF(H15="绿灯",0,IF(H15="黄灯",1,IF(H15="红灯",2,"")))) | L15: 新闻聚类 | M15: Google News RSS / 主流媒体
A16: TR-06 | B16: 中期传导 | C16: 资金链 | D16: 仓储融资 / 回购 / 过桥融资成本是否抬升 | E16: 每月 | F16: warehouse financing 是否更贵、更短、更难续 | G16: 融资成本上升=黄灯；续作困难=红灯 | H16: 待更新 | I16: =IF(H16="待更新","",IF(H16="绿灯",0,IF(H16="黄灯",1,IF(H16="红灯",2,"")))) | L16: 代理数值 | M16: FRED
A17: SY-01 | B17: 系统确认 | C17: 银行传导 | D17: 银行是否收紧对相关领域授信 | E17: 每季 | F17: 中型企业、杠杆融资、相关非银授信标准是否收紧 | G17: 授信收紧=黄灯；明显抽贷 / 断贷=红灯 | H17: 待更新 | I17: =IF(H17="待更新","",IF(H17="绿灯",0,IF(H17="黄灯",1,IF(H17="红灯",2,"")))) | L17: 代理数值 | M17: FRED + Stooq
... A21: SY-05 | B21: 系统确认 | C21: 实体经济 | D21: 中小企业再融资是否明显失败 | E21: 每季 | F21: 再融资失败率、破产、裁员、CAPEX 收缩 | G21: 融资失败增多=黄灯；实体信用收缩明显=红灯 | H21: 待更新 | I21: =IF(H21="待更新","",IF(H21="绿灯",0,IF(H21="黄灯",1,IF(H21="红灯",2,"")))) | L21: 新闻聚类 | M21: Google News RSS / 主流媒体
A24: 判定建议
A25: 绿灯
A26: 黄灯
A27: 红灯

Sheet Evidence
A1: Evidence ID | B1: 指标ID | C1: 媒体 | D1: 标题 | E1: 日期 | F1: 链接

Sheet Lists
A1: 待更新
A2: 绿灯
A3: 黄灯
A4: 红灯

Sheet AutomationMap
A1: ID | B1: 层级 | C1: 指标 | D1: 自动化方式 | E1: 主数据源 | F1: 说明
A2: EW-01 | B2: 早期预警 | C2: 是否出现新的限赎 / Gate | D2: 新闻聚类 | E2: Google News RSS / 主流媒体 | F2: 新闻型指标请结合 Evidence sheet 复核；数值型指标由脚本自动写入状态依据。
A3: EW-02 | B3: 早期预警 | C3: 相关资管股是否持续跑输 | D3: 数值直抓 | E3: Stooq | F3: 新闻型指标请结合 Evidence sheet 复核；数值型指标由脚本自动写入状态依据。
A4: EW-03 | B4: 早期预警 | C4: BDC 板块是否扩大折价 | D4: 代理数值 | E4: Stooq | F4: 新闻型指标请结合 Evidence sheet 复核；数值型指标由脚本自动写入状态依据。
A5: EW-04 | B5: 早期预警 | C5: HY / 杠杆贷款 / CLO 是否同步走弱 | D5: 数值直抓 | E5: FRED + Stooq | F5: 新闻型指标请结合 Evidence sheet 复核；数值型指标由脚本自动写入状态依据。
A6: EW-05 | B6: 早期预警 | C6: 坏消息是否从个案变成簇发 | D6: 新闻聚类 | E6: Google News RSS / 主流媒体 | F6: 新闻型指标请结合 Evidence sheet 复核；数值型指标由脚本自动写入状态依据。
A7: TR-01 | B7: 中期传导 | C7: 违约 / 重组 / 展期是否增加 | D7: 新闻聚类 | E7: Google News RSS / 主流媒体 | F7: 新闻型指标请结合 Evidence sheet 复核；数值型指标由脚本自动写入状态依据。
A8: TR-02 | B8: 中期传导 | C8: PIK 利息是否增多 | D8: 新闻聚类 | E8: Google News RSS / 主流媒体 | F8: 新闻型指标请结合 Evidence sheet 复核；数值型指标由脚本自动写入状态依据。
A9: TR-03 | B9: 中期传导 | C9: NAV 是否开始连续下修 | D9: 代理数值 | E9: Stooq | F9: 新闻型指标请结合 Evidence sheet 复核；数值型指标由脚本自动写入状态依据。
A10: TR-04 | B10: 中期传导 | C10: 新基金募资是否明显放缓 | D10: 新闻聚类 | E10: Google News RSS / 主流媒体 | F10: 新闻型指标请结合 Evidence sheet 复核；数值型指标由脚本自动写入状态依据。
A11: TR-05 | B11: 中期传导 | C11: 新交易条款是否重新收紧 | D11: 新闻聚类 | E11: Google News RSS / 主流媒体 | F11: 新闻型指标请结合 Evidence sheet 复核；数值型指标由脚本自动写入状态依据。
A12: TR-06 | B12: 中期传导 | C12: 仓储融资 / 回购 / 过桥融资成本是否抬升 | D12: 代理数值 | E12: FRED | F12: 新闻型指标请结合 Evidence sheet 复核；数值型指标由脚本自动写入状态依据。
... A17: SY-05 | B17: 系统确认 | C17: 中小企业再融资是否明显失败 | D17: 新闻聚类 | E17: Google News RSS / 主流媒体 | F17: 新闻型指标请结合 Evidence sheet 复核；数值型指标由脚本自动写入状态依据。
